{
    "success": true,
    "result": [
        [
            {
                "Profile": "Imran Syed",
                "Folder Name": "My first Folder",
                "LinkedIn ID": "imran-syed-aba51052",
                "Full Name": "Imran Syed",
                "First Name": "Imran",
                "Last Name": "Syed",
                "About": "Imran Syed has experience in various domain, starting from Learning and Development, Leading a team to delivery projects on time and facilitating various other company to implement experts proven techniques.Imran Syed's Individual Consltant helping those professionals \"Who has experience but do not grow up the ladder\", someone \"Who who deserves to get projects from clients, but just fails for not having any certification to show in there profile\".Independent venture on Education Management is fast growing organization on Professional training and certification from various governing bodies.I facilitates training for Clients - Onsite and Public. Currently we deliver training on more than 78 courses to name few. CAPM, PMP, PRINCE2, Project Management, IT Service Management, Quality Management and Agile & Scrum.",
                "Country": "United Arab Emirates",
                "City": "United Arab Emirates",
                "Company": "Sprintzeal",
                "Company Logo Url": "https://masdfasdfedia.licasdfasdfdn.com/dms/image/v2/C5103AQGiScfvxOfBoQ/profile-displayphoto-shrink_400_400/profile-displayphoto-shrink_400_400/0/1564752034473?e=1730332800&v=beta&t=HjFGHd4davPJ8TgpXbmm8lqCDRniwEpYgBsp6at5npkasfasfasfasf",
                "Current Position": "CEO | Trainer | Speaker | Upcoming Author | Angel Investor",
                "Current Position Experience": "8 Yrs, 4 Months",
                "Current Company Industry": "Education",
                "Past Postion": "Co-Founder",
                "Past Position Experience": "2 Yrs, 7 Months",
                "Skills": "Serial Entrepreneur & CEO at Sprintzeal | Trainer | Speaker | Upcoming Book Author at Sprintzeal",
                "Education": "Master of Business Administration (MBA), International Marketing",
                "Profile Image Url": "https://media.licdn.com/dms/image/v2/C5103AQGiScfvxOfBoQ/profile-displayphoto-shrink_400_400/profile-displayphoto-shrink_400_400/0/1564752034473?e=1730332800&v=beta&t=HjFGHd4davPJ8TgpXbmm8lqCDRniwEpYgBsp6at5npk",
                "Primary Work Email": "syed.imran@sprintzeal.com",
                "Personal Email": "syedemran1@gmail.com",
                "Other Email": "syedemran111@hotmail.com, syedemran2211@redifmail.com, syedimran@yahoo.com",
                "Email Status": "Sequence Assigned",
                "Work Phone": 91984747474,
                "Personal Phone": 918738000000,
                "Other Phone": "456789, 34567890, 3456789",
                "Template": "PMP Template",
                "Assigned Sequence Status": "Yes",
                "Update From LinkedIn": "8/27/24",
                "Created At": "8/27/24",
                "Updated Date": "8/27/24",
                "Lead Status": "Warm",
                "Profile LinkedIn Url": "https://www.linkedin.com/in/imran-syed-aba51052/",
                "Company Domain": "www.sprintzeal.com",
                "Company Size": "51-200"
            }
        ]
    ]
}